docs-source/conf.py
examples/extract.py
examples/pdf.py
examples/screenshot.py
examples/screenshot_json.py
examples/screenshot_webp.py
examples/scrolling_video_json.py
examples/video_json.py
webshotapi/__init__.py
webshotapi/client.py
webshotapi/client_exception.py
webshotapi/types.py
webshotapi/version.py
webshotapi-1.1.16.dist-info/licenses/LICENSE
webshotapi-1.1.16.dist-info/METADATA
webshotapi-1.1.16.dist-info/WHEEL
webshotapi-1.1.16.dist-info/top_level.txt
webshotapi-1.1.16.dist-info/RECORD
