Metadata-Version: 2.4
Name: webshotapi
Version: 1.1.16
Summary: Api client for WebShotApi.com. Website screenshot api client, extract html from rendered website extract words with coordinates from website, extract styles from HTML selectors(elements)
Author-email: "WebShotApi.com" <contact@webshotapi.com>
License-Expression: MIT
Project-URL: Homepage, https://webshotapi.com
Project-URL: Issues, https://github.com/webshotapi/python-client/issues
Project-URL: Documentation, https://webshotapi.com/docs/sdk/python/
Project-URL: Repository, https://github.com/webshotapi/python-client
Keywords: screenshot,api,webshotapi,html,extract,ocr,scrolling video,video,cookie remove
Classifier: Programming Language :: Python :: 3
Classifier: Operating System :: OS Independent
Requires-Python: >=3.8
License-File: LICENSE
Requires-Dist: six
Requires-Dist: urllib3
Requires-Dist: gawsoft-api-client>=0.1.12
Requires-Dist: requests
Dynamic: license-file
